{
    "directory": [
        {
            "name": "Jolibee",
            "addresses": "Daet Camarines Norte",
            "phone": "+639123456789",
            "website": "https://fireburn553.github.io/wdd230/",
            "image": "https://github.com/fireburn553/wdd230/blob/main/chamber/images/sample_icon.png"
        },
        {
            "name": "SM City Daet",
            "addresses": "Daet Camarines Norte",
            "phone": "+639123456789",
            "website": "https://fireburn553.github.io/wdd230/",
            "image": "https://github.com/fireburn553/wdd230/blob/main/chamber/images/sample_icon.png"
        },
        {
            "name": "LBC",
            "addresses": "Daet Camarines Norte",
            "phone": "+639123456789",
            "website": "https://fireburn553.github.io/wdd230/",
            "image": "https://github.com/fireburn553/wdd230/blob/main/chamber/images/sample_icon.png"
        },
        {
            "name": "Premium Bikes",
            "addresses": "Daet Camarines Norte",
            "phone": "+639123456789",
            "website": "https://fireburn553.github.io/wdd230/",
            "image": "https://github.com/fireburn553/wdd230/blob/main/chamber/images/sample_icon.png"
        },
        {
            "name": "Shell",
            "addresses": "Daet Camarines Norte",
            "phone": "+639123456789",
            "website": "https://fireburn553.github.io/wdd230/",
            "image": "https://github.com/fireburn553/wdd230/blob/main/chamber/images/sample_icon.png"
        },
        {
            "name": "Cafe Morga",
            "addresses": "Daet Camarines Norte",
            "phone": "+639123456789",
            "website": "https://fireburn553.github.io/wdd230/",
            "image": "https://github.com/fireburn553/wdd230/blob/main/chamber/images/sample_icon.png"
        },
        {
            "name": "Meat Land",
            "addresses": "Daet Camarines Norte",
            "phone": "+639123456789",
            "website": "https://fireburn553.github.io/wdd230/",
            "image": "https://github.com/fireburn553/wdd230/blob/main/chamber/images/sample_icon.png"
        },
        {
            "name": "ACLC",
            "addresses": "Daet Camarines Norte",
            "phone": "+639123456789",
            "website": "https://fireburn553.github.io/wdd230/",
            "image": "https://github.com/fireburn553/wdd230/blob/main/chamber/images/sample_icon.png"
        },
        {
            "name": "Business9",
            "addresses": "Daet Camarines Norte",
            "phone": "+639123456789",
            "website": "https://fireburn553.github.io/wdd230/",
            "image": "https://github.com/fireburn553/wdd230/blob/main/chamber/images/sample_icon.png"
        },
        {
            "name": "Business10",
            "addresses": "Daet Camarines Norte",
            "phone": "+639123456789",
            "website": "https://fireburn553.github.io/wdd230/",
            "image": "https://github.com/fireburn553/wdd230/blob/main/chamber/images/sample_icon.png"
        },
        {
            "name": "Business11",
            "addresses": "Daet Camarines Norte",
            "phone": "+639123456789",
            "website": "https://fireburn553.github.io/wdd230/",
            "image": "https://github.com/fireburn553/wdd230/blob/main/chamber/images/sample_icon.png"
        },
        {
            "name": "Business12",
            "addresses": "Daet Camarines Norte",
            "phone": "+639123456789",
            "website": "https://fireburn553.github.io/wdd230/",
            "image": "https://github.com/fireburn553/wdd230/blob/main/chamber/images/sample_icon.png"
        }
    ]
  }